{
	"info": {
		"_postman_id": "3a9a77be-3feb-4013-9442-49c73618312d",
		"name": "DigitalBank - Apis",
		"schema": "https://schema.getpostman.com/json/collection/v2.1.0/collection.json"
	},
	"item": [
		{
			"name": "Cliente",
			"item": [
				{
					"name": "Conta 1",
					"request": {
						"method": "POST",
						"header": [
							{
								"key": "Content-Type",
								"name": "Content-Type",
								"value": "application/json",
								"type": "text"
							}
						],
						"body": {
							"mode": "raw",
							"raw": "{\n\t\"nome\": \"João\",\n\t\"cpf\": \"22985315875\",\n\t\"telefone\": 991059200,\n\t\"rendaMensal\": 10000.00,\n\t\"logradouro\": \"Rua Nardina Rodrigues Johansen\",\n\t\"numero\": 159,\n\t\"complemento\": \"Bloco 3, Apto 402\",\n\t\"bairro\": \"Loteamento Malbec\",\n\t\"cidade\": \"Maringá\",\n\t\"estado\": \"PR\",\n\t\"cep\": \"87005002\"\n}",
							"options": {
								"raw": {
									"language": "json"
								}
							}
						},
						"url": {
							"raw": "http://localhost:8080/api/v1/clientes",
							"protocol": "http",
							"host": [
								"localhost"
							],
							"port": "8080",
							"path": [
								"api",
								"v1",
								"clientes"
							]
						}
					},
					"response": []
				},
				{
					"name": "Conta 2",
					"request": {
						"method": "POST",
						"header": [
							{
								"key": "Content-Type",
								"name": "Content-Type",
								"type": "text",
								"value": "application/json"
							}
						],
						"body": {
							"mode": "raw",
							"raw": "{\n\t\"nome\": \"Pedro\",\n\t\"cpf\": \"05223551966\",\n\t\"telefone\": 997115453,\n\t\"rendaMensal\": 10000.00,\n\t\"logradouro\": \"Rua Nardina Rodrigues Johansen\",\n\t\"numero\": 159,\n\t\"complemento\": \"Bloco 3, Apto 402\",\n\t\"bairro\": \"Loteamento Malbec\",\n\t\"cidade\": \"Maringá\",\n\t\"estado\": \"PR\",\n\t\"cep\": \"87005002\"\n}",
							"options": {
								"raw": {
									"language": "json"
								}
							}
						},
						"url": {
							"raw": "http://localhost:8080/api/v1/clientes",
							"protocol": "http",
							"host": [
								"localhost"
							],
							"port": "8080",
							"path": [
								"api",
								"v1",
								"clientes"
							]
						}
					},
					"response": []
				},
				{
					"name": "Consultar",
					"protocolProfileBehavior": {
						"disableBodyPruning": true
					},
					"request": {
						"method": "GET",
						"header": [
							{
								"key": "Content-Type",
								"name": "Content-Type",
								"type": "text",
								"value": "application/json"
							}
						],
						"body": {
							"mode": "raw",
							"raw": "{\n\t\"nome\": \"Pedro\",\n\t\"cpf\": \"05223551966\",\n\t\"telefone\": 997115453,\n\t\"rendaMensal\": 10000.00,\n\t\"logradouro\": \"Rua Nardina Rodrigues Johansen\",\n\t\"numero\": 159,\n\t\"complemento\": \"Bloco 3, Apto 402\",\n\t\"bairro\": \"Loteamento Malbec\",\n\t\"cidade\": \"Maringá\",\n\t\"estado\": \"PR\",\n\t\"cep\": \"87005002\"\n}",
							"options": {
								"raw": {
									"language": "json"
								}
							}
						},
						"url": {
							"raw": "http://localhost:8080/api/v1/clientes/1",
							"protocol": "http",
							"host": [
								"localhost"
							],
							"port": "8080",
							"path": [
								"api",
								"v1",
								"clientes",
								"1"
							]
						}
					},
					"response": []
				},
				{
					"name": "Atualizar",
					"request": {
						"method": "PUT",
						"header": [
							{
								"key": "Content-Type",
								"name": "Content-Type",
								"type": "text",
								"value": "application/json"
							}
						],
						"body": {
							"mode": "raw",
							"raw": "{\n\t\"nome\": \"Pedro\",\n\t\"cpf\": \"05223551966\",\n\t\"telefone\": 997115453,\n\t\"rendaMensal\": 10000.00,\n\t\"logradouro\": \"Rua\",\n\t\"numero\": 1,\n\t\"complemento\": \"Bloco\",\n\t\"bairro\": \"Loteamento\",\n\t\"cidade\": \"Mari\",\n\t\"estado\": \"SP\",\n\t\"cep\": \"87005001\"\n}",
							"options": {
								"raw": {
									"language": "json"
								}
							}
						},
						"url": {
							"raw": "http://localhost:8080/api/v1/clientes/1",
							"protocol": "http",
							"host": [
								"localhost"
							],
							"port": "8080",
							"path": [
								"api",
								"v1",
								"clientes",
								"1"
							]
						}
					},
					"response": []
				}
			],
			"protocolProfileBehavior": {}
		},
		{
			"name": "Conta",
			"item": [
				{
					"name": "Depositar",
					"request": {
						"method": "POST",
						"header": [
							{
								"key": "Content-Type",
								"name": "Content-Type",
								"type": "text",
								"value": "application/json"
							}
						],
						"body": {
							"mode": "raw",
							"raw": "{\n\t\"valor\": 100.00\n}",
							"options": {
								"raw": {
									"language": "json"
								}
							}
						},
						"url": {
							"raw": "http://localhost:8080/api/v1/contas/1/depositar",
							"protocol": "http",
							"host": [
								"localhost"
							],
							"port": "8080",
							"path": [
								"api",
								"v1",
								"contas",
								"1",
								"depositar"
							]
						}
					},
					"response": []
				},
				{
					"name": "Sacar",
					"request": {
						"method": "POST",
						"header": [
							{
								"key": "Content-Type",
								"name": "Content-Type",
								"type": "text",
								"value": "application/json"
							}
						],
						"body": {
							"mode": "raw",
							"raw": "{\n\t\"valor\": 10.00\n}",
							"options": {
								"raw": {
									"language": "json"
								}
							}
						},
						"url": {
							"raw": "http://localhost:8080/api/v1/contas/1/sacar",
							"protocol": "http",
							"host": [
								"localhost"
							],
							"port": "8080",
							"path": [
								"api",
								"v1",
								"contas",
								"1",
								"sacar"
							]
						}
					},
					"response": []
				},
				{
					"name": "Pagar",
					"request": {
						"method": "POST",
						"header": [
							{
								"key": "Content-Type",
								"name": "Content-Type",
								"type": "text",
								"value": "application/json"
							}
						],
						"body": {
							"mode": "raw",
							"raw": "{\n\t\"valor\": 20.00,\n\t\"descricao\": \"Boleto\"\n}",
							"options": {
								"raw": {
									"language": "json"
								}
							}
						},
						"url": {
							"raw": "http://localhost:8080/api/v1/contas/1/pagar",
							"protocol": "http",
							"host": [
								"localhost"
							],
							"port": "8080",
							"path": [
								"api",
								"v1",
								"contas",
								"1",
								"pagar"
							]
						}
					},
					"response": []
				},
				{
					"name": "Transferir",
					"request": {
						"method": "POST",
						"header": [
							{
								"key": "Content-Type",
								"name": "Content-Type",
								"value": "application/json",
								"type": "text"
							}
						],
						"body": {
							"mode": "raw",
							"raw": "{\n\t\"numeroAgencia\": 1,\n\t\"numeroConta\": 997115453,\n\t\"valor\": 30,\n\t\"descricao\": \"Churrasco\"\n}",
							"options": {
								"raw": {
									"language": "json"
								}
							}
						},
						"url": {
							"raw": "http://localhost:8080/api/v1/contas/1/transferir",
							"protocol": "http",
							"host": [
								"localhost"
							],
							"port": "8080",
							"path": [
								"api",
								"v1",
								"contas",
								"1",
								"transferir"
							]
						}
					},
					"response": []
				},
				{
					"name": "Consultar extrato completo",
					"protocolProfileBehavior": {
						"disableBodyPruning": true
					},
					"request": {
						"method": "GET",
						"header": [
							{
								"key": "Content-Type",
								"name": "Content-Type",
								"value": "application/json",
								"type": "text"
							}
						],
						"body": {
							"mode": "raw",
							"raw": "{\n\t\"numeroConta\": 997115453,\n\t\"valor\": 35.00,\n\t\"descricao\": \"Churrasco\"\n}",
							"options": {
								"raw": {
									"language": "json"
								}
							}
						},
						"url": {
							"raw": "http://localhost:8080/api/v1/contas/1/lancamentos",
							"protocol": "http",
							"host": [
								"localhost"
							],
							"port": "8080",
							"path": [
								"api",
								"v1",
								"contas",
								"1",
								"lancamentos"
							]
						}
					},
					"response": []
				}
			],
			"protocolProfileBehavior": {}
		}
	],
	"protocolProfileBehavior": {}
}